{
  "date": "2026-03-02",
  "platform": "Apple Music",
  "scope": "US",
  "source": "Apple Marketing Tools",
  "items": [
    {
      "rank": 1,
      "track": "Risk It All",
      "artist": "Bruno Mars"
    },
    {
      "rank": 2,
      "track": "Choosin' Texas",
      "artist": "Ella Langley"
    },
    {
      "rank": 3,
      "track": "I Just Might",
      "artist": "Bruno Mars"
    },
    {
      "rank": 4,
      "track": "E85",
      "artist": "Don Toliver"
    },
    {
      "rank": 5,
      "track": "DtMF",
      "artist": "Bad Bunny"
    },
    {
      "rank": 6,
      "track": "Man I Need",
      "artist": "Olivia Dean"
    },
    {
      "rank": 7,
      "track": "Be Her",
      "artist": "Ella Langley"
    },
    {
      "rank": 8,
      "track": "BAILE INoLVIDABLE",
      "artist": "Bad Bunny"
    },
    {
      "rank": 9,
      "track": "Stateside (with Zara Larsson)",
      "artist": "PinkPantheress"
    },
    {
      "rank": 10,
      "track": "Body",
      "artist": "Don Toliver"
    },
    {
      "rank": 11,
      "track": "Cha Cha Cha",
      "artist": "Bruno Mars"
    },
    {
      "rank": 12,
      "track": "Be By You",
      "artist": "Luke Combs"
    },
    {
      "rank": 13,
      "track": "Why You Wanna Fight?",
      "artist": "Bruno Mars"
    },
    {
      "rank": 14,
      "track": "God Was Showing Off",
      "artist": "Bruno Mars"
    },
    {
      "rank": 15,
      "track": "Ordinary",
      "artist": "Alex Warren"
    },
    {
      "rank": 16,
      "track": "Good Days",
      "artist": "SZA"
    },
    {
      "rank": 17,
      "track": "Freestyle",
      "artist": "Lil Baby"
    },
    {
      "rank": 18,
      "track": "Tití Me Preguntó",
      "artist": "Bad Bunny"
    },
    {
      "rank": 19,
      "track": "In A Minute",
      "artist": "Lil Baby"
    },
    {
      "rank": 20,
      "track": "FDO",
      "artist": "Pooh Shiesty"
    },
    {
      "rank": 21,
      "track": "What I Want",
      "artist": "Morgan Wallen & Tate McRae"
    },
    {
      "rank": 22,
      "track": "I'm The Problem",
      "artist": "Morgan Wallen"
    },
    {
      "rank": 23,
      "track": "So Easy (To Fall In Love)",
      "artist": "Olivia Dean"
    },
    {
      "rank": 24,
      "track": "What You Saying",
      "artist": "Lil Uzi Vert"
    },
    {
      "rank": 25,
      "track": "On My Soul",
      "artist": "Bruno Mars"
    },
    {
      "rank": 26,
      "track": "Folded",
      "artist": "Kehlani"
    },
    {
      "rank": 27,
      "track": "WAIT FOR U (feat. Drake & Tems)",
      "artist": "Future"
    },
    {
      "rank": 28,
      "track": "Golden",
      "artist": "HUNTR/X, EJAE, AUDREY NUNA, REI AMI & KPop Demon Hunters Cast"
    },
    {
      "rank": 29,
      "track": "Die On This Hill",
      "artist": "SIENNA SPIRO"
    },
    {
      "rank": 30,
      "track": "Dance With Me",
      "artist": "Bruno Mars"
    },
    {
      "rank": 31,
      "track": "iloveitiloveitiloveit",
      "artist": "Bella Kay"
    },
    {
      "rank": 32,
      "track": "Chasin' You",
      "artist": "Morgan Wallen"
    },
    {
      "rank": 33,
      "track": "March Madness",
      "artist": "Future"
    },
    {
      "rank": 34,
      "track": "The Fate of Ophelia",
      "artist": "Taylor Swift"
    },
    {
      "rank": 35,
      "track": "LIKE ME (feat. 42 Dugg & Lil Baby)",
      "artist": "Future"
    },
    {
      "rank": 36,
      "track": "Just In Case",
      "artist": "Morgan Wallen"
    },
    {
      "rank": 37,
      "track": "NUEVAYoL",
      "artist": "Bad Bunny"
    },
    {
      "rank": 38,
      "track": "Last Night",
      "artist": "Morgan Wallen"
    },
    {
      "rank": 39,
      "track": "Vete",
      "artist": "Bad Bunny"
    },
    {
      "rank": 40,
      "track": "Frozen",
      "artist": "Lil Baby"
    }
  ]
}